{
  "appPageId" : "90c14252-889a-4b26-a3af-b3e5f74f0f02",
  "componentName" : "siteforce:sldsOneColLayout",
  "dataProviders" : [ ],
  "id" : "66523ef0-4c75-447f-ba1b-a13c49f3e54f",
  "label" : "User Profile",
  "regions" : [ {
    "id" : "db465af6-9375-4eaf-b4b4-cfd5fec3b998",
    "regionName" : "header",
    "type" : "region"
  }, {
    "components" : [ {
      "componentAttributes" : {
        "caseCreateLabel" : "Create Case",
        "caseFilterName" : "AllOpenCases",
        "caseHeaderLabel" : "My Cases",
        "casesTabLabel" : "Cases",
        "detailsTabLabel" : "Details",
        "feedTabLabel" : "Feed",
        "knowledgeableAboutTitle" : "Knows About",
        "maxTopics" : 5,
        "recognitionbuttonLabel" : "Give",
        "relatedTabLabel" : "Related",
        "showAllUpdates" : false,
        "showBadges" : true,
        "showFullPhotoAsCircle" : true,
        "showKnowledgeableAbout" : true,
        "showRelatedList" : true,
        "showReputationInInfluenceCard" : false,
        "showStats" : true,
        "userBadgesTitle" : "Recognition Badges",
        "userId" : "{!recordId}",
        "userStatsTitle" : "Influence"
      },
      "componentName" : "forceCommunity:userRecordHome",
      "id" : "2135608e-a2e5-44a3-853b-ed4b8651d330",
      "renderPriority" : "NEUTRAL",
      "renditionMap" : { },
      "type" : "component"
    } ],
    "id" : "f207d3bb-ccf4-42b6-ab32-8e8ad95a8ed1",
    "regionName" : "content",
    "type" : "region"
  }, {
    "id" : "d06b2260-535d-447e-bb20-2a672c4b4e86",
    "regionName" : "footer",
    "type" : "region"
  } ],
  "themeLayoutType" : "Inner",
  "type" : "view",
  "viewType" : "detail-005"
}